README.md
README.rst
setup.py
dump/__init__.py
dump/__main__.py
dump/postgres.py
dump.egg-info/PKG-INFO
dump.egg-info/SOURCES.txt
dump.egg-info/dependency_links.txt
dump.egg-info/entry_points.txt
dump.egg-info/top_level.txt
dump/interface/__init__.py
dump/interface/postgres.py